cerebro_client/__init__.py
cerebro_client/client.py
cerebro_client-1.0.0.dist-info/METADATA
cerebro_client-1.0.0.dist-info/WHEEL
cerebro_client-1.0.0.dist-info/top_level.txt
cerebro_client-1.0.0.dist-info/RECORD
