Metadata-Version: 2.1
Name: cerebro-client
Version: 1.0.0
Summary: Cliente Python para interactuar con la API de Cerebro Trading.
Home-page: UNKNOWN
Author: Percy Guerra
Author-email: percy.guerra1@unmsm.edu.pe
License: UNKNOWN
Platform: UNKNOWN
Classifier: Programming Language :: Python :: 3
Classifier: License :: OSI Approved :: MIT License
Classifier: Operating System :: OS Independent
Requires-Python: >=3.7
Requires-Dist: requests >=2.20.0
Requires-Dist: pandas >=1.0.0
